MANIFEST.in
README.rst
setup.py
aloha/__init__.py
aloha/urls.py
aloha/views.py
aloha/templates/aloha/postform.html
aloha/templates/aloha/includes/css.html
aloha/templates/aloha/includes/js.html
aloha/templatetags/__init__.py
aloha/templatetags/aloha_tags.py
django_aloha.egg-info/PKG-INFO
django_aloha.egg-info/SOURCES.txt
django_aloha.egg-info/dependency_links.txt
django_aloha.egg-info/top_level.txt