Metadata-Version: 1.0
Name: django-aloha
Version: 0.0.1
Summary: django app to easily integrate editing with Aloha WYSIWIG editor in django apps.
Home-page: https://bitbucket.org/descent/django-aloha
Author: Igor Katson
Author-email: igor.katson@gmail.com
License: UNKNOWN
Platform: UNKNOWN
Classifier: Development Status :: 3 - Alpha
Classifier: Intended Audience :: Developers
Classifier: License :: OSI Approved :: GNU General Public License (GPL)
Classifier: Operating System :: POSIX
Classifier: Programming Language :: Python
Classifier: Topic :: Software Development :: Libraries :: Python Modules
Classifier: Topic :: Internet :: WWW/HTTP :: Dynamic Content
